{
    "activityLog": [
        {
            "type": "Extension Proctoring",
            "timeStampInVideo": "00:00:12",
            "activityDescription": "Window change detected",
            "count": 1
        },
        {
            "type": "Extension Proctoring",
            "timeStampInVideo": "00:00:15",
            "activityDescription": "Window change detected",
            "count": 1
        },
        {
            "type": "Extension Proctoring",
            "timeStampInVideo": "00:00:15",
            "activityDescription": "Browser window swapped",
            "count": 2
        },
        {
            "type": "Extension Proctoring",
            "timeStampInVideo": "00:03:47",
            "activityDescription": "Window change detected",
            "count": 2
        },
        {
            "type": "Extension Proctoring",
            "timeStampInVideo": "00:15:16",
            "activityDescription": "Browser window swapped",
            "count": 1
        },
        {
            "type": "Extension Proctoring",
            "timeStampInVideo": "NaN:NaN:NaN",
            "activityDescription": "Window change detected",
            "count": 1
        }
    ]
}